Metadata-Version: 2.4
Name: swcgeom
Version: 0.21.2
Summary: Neuron geometry library for swc format
Author-email: yzx9 <pypi@yzx9.xyz>
License-Expression: Apache-2.0
Project-URL: repository, https://github.com/yzx9/swcgeom
Keywords: neuroscience,neuron,neuroanatomy,neuron-morphology
Classifier: Development Status :: 4 - Beta
Classifier: Operating System :: OS Independent
Classifier: Programming Language :: Python :: 3 :: Only
Classifier: Programming Language :: Python :: 3.10
Classifier: Programming Language :: Python :: 3.11
Classifier: Programming Language :: Python :: 3.12
Classifier: Programming Language :: Python :: 3.13
Classifier: Intended Audience :: Science/Research
Classifier: Intended Audience :: Developers
Classifier: Topic :: Scientific/Engineering :: Bio-Informatics
Classifier: Topic :: Scientific/Engineering :: Visualization
Requires-Python: >=3.10
License-File: LICENSE
Requires-Dist: imagecodecs>=2023.3.16
Requires-Dist: matplotlib>=3.5.2
Requires-Dist: numpy>=1.22.3
Requires-Dist: pandas>=1.4.2
Requires-Dist: pynrrd>=1.1.0
Requires-Dist: scipy>=1.9.1
Requires-Dist: sdflit>=0.2.6
Requires-Dist: seaborn>=0.12.0
Requires-Dist: tifffile>=2022.8.12
Requires-Dist: typing-extensions>=4.4.0
Requires-Dist: tqdm>=4.46.1
Provides-Extra: all
Requires-Dist: beautifulsoup4>=4.11.1; extra == "all"
Requires-Dist: certifi>=2023.5.7; extra == "all"
Requires-Dist: chardet>=5.2.0; extra == "all"
Requires-Dist: lmdb>=1.4.1; extra == "all"
Requires-Dist: requests>=2.0.0; extra == "all"
Requires-Dist: urllib3>=1.26.0; extra == "all"
Dynamic: license-file
